tests/__init__.py
tests/test_classification.py
tests/test_encoder_model.py
tests/test_parser.py
tests/test_tagger.py
tfnlu/__init__.py
tfnlu/version.txt
tfnlu/classification/__init__.py
tfnlu/classification/classification.py
tfnlu/classification/classification_model.py
tfnlu/classification/get_tags.py
tfnlu/classification/to_tags.py
tfnlu/classification/to_tokens.py
tfnlu/parser/__init__.py
tfnlu/parser/biaffine.py
tfnlu/parser/draw_dp.py
tfnlu/parser/get_tags.py
tfnlu/parser/parser.py
tfnlu/parser/parser_model.py
tfnlu/parser/pos_get_tags.py
tfnlu/parser/pos_to_tags.py
tfnlu/parser/pos_to_tokens.py
tfnlu/parser/to_tags.py
tfnlu/parser/to_tokens.py
tfnlu/tagger/__init__.py
tfnlu/tagger/check_validation.py
tfnlu/tagger/crf.py
tfnlu/tagger/extract_entities.py
tfnlu/tagger/get_sets.py
tfnlu/tagger/get_tags.py
tfnlu/tagger/score_table.py
tfnlu/tagger/tagger.py
tfnlu/tagger/tagger_model.py
tfnlu/tagger/tagger_pointer_model.py
tfnlu/tagger/to_pointer_tags.py
tfnlu/tagger/to_pointer_tokens.py
tfnlu/tagger/to_tags.py
tfnlu/tagger/to_tokens.py
tfnlu/utils/__init__.py
tfnlu/utils/config.py
tfnlu/utils/draw_dp.py
tfnlu/utils/encoder_model.py
tfnlu/utils/logger.py
tfnlu/utils/serialize_dir.py
tfnlu/utils/tfnlu_model.py
tfnlu/utils/transformer.py
tfnlu-1.1.4.dist-info/LICENSE
tfnlu-1.1.4.dist-info/METADATA
tfnlu-1.1.4.dist-info/WHEEL
tfnlu-1.1.4.dist-info/top_level.txt
tfnlu-1.1.4.dist-info/RECORD
