Metadata-Version: 2.1
Name: tfnlu
Version: 1.1.4
Summary: NLP tool
Home-page: https://github.com/deepdialog/tfnlu
Author: deepdialog
Author-email: thebotbot@sina.com
License: Private
Keywords: nlp,tensorflow,parser,tagger
Platform: any
Requires-Dist: pandas
Requires-Dist: tensorflow-addons
Requires-Dist: tensorflow-hub
Requires-Dist: tensorflow (>=2.2.0)
Requires-Dist: tqdm
